Metadata-Version: 1.0
Name: aws-list-subnets
Version: 0.1.2
Summary: list aws subnets
Home-page: UNKNOWN
Author: suzuki-navi
Author-email: UNKNOWN
License: UNKNOWN
Platform: UNKNOWN
